zih_clients/__init__.py
zih_clients/py.typed
zih_clients/znuny/__init__.py
zih_clients/znuny/connection.py
zih_clients/znuny/connection_test.py
zih_clients/znuny/manager.py
zih_clients/znuny/manager_test.py
zih_clients/znuny/models.py
zih_clients/znuny/types.py
zih_clients-0.1.2.dist-info/LICENSE
zih_clients-0.1.2.dist-info/METADATA
zih_clients-0.1.2.dist-info/WHEEL
zih_clients-0.1.2.dist-info/RECORD
