Metadata-Version: 2.3
Name: zih-clients
Version: 0.1.2
Summary: client libraries for HTTP APIs
License: MIT
Author: Ansgar Burchardt
Author-email: ansgar.burchardt@tu-dresden.de
Requires-Python: >=3.11
Classifier: Programming Language :: Python :: 3
Classifier: Operating System :: OS Independent
Requires-Dist: httpx (>=0.28.1,<0.29.0)
Requires-Dist: pydantic (>=2.11.7,<3.0.0)
Project-URL: Repository, https://gitlab.hrz.tu-chemnitz.de/zih/sde/zih-clients
